README.md
setup.cfg
setup.py
MSOIsHH2dsdsdsos.egg-info/PKG-INFO
MSOIsHH2dsdsdsos.egg-info/SOURCES.txt
MSOIsHH2dsdsdsos.egg-info/dependency_links.txt
MSOIsHH2dsdsdsos.egg-info/top_level.txt
flood_tool/__init__.py
flood_tool/analysis.py
flood_tool/geo.py
flood_tool/live.py
flood_tool/mapping.py
flood_tool/tool.py